weird_converter/__init__.py
weird_converter/config.py
weird_converter-0.2.dist-info/LICENSE
weird_converter-0.2.dist-info/METADATA
weird_converter-0.2.dist-info/WHEEL
weird_converter-0.2.dist-info/top_level.txt
weird_converter-0.2.dist-info/RECORD
