Metadata-Version: 2.1
Name: weird-converter
Version: 0.2
Summary: Strange combinations converter
Home-page: https://github.com/AlbertSuarez/weird-converter
Author: AlbertSuarez
Author-email: alsumo95@gmail.com
License: Apache-2.0
Keywords: converter audio image audio-to-image image-to-audio
Platform: UNKNOWN
Classifier: Programming Language :: Python :: 3
Classifier: Operating System :: OS Independent
Requires-Dist: numpy (==1.18.4)
Requires-Dist: Pillow (==7.1.2)
Requires-Dist: scipy (==1.4.1)
